hikaru/model/rel_1_23/__init__.py
hikaru/model/rel_1_23/deprecations.py
hikaru/model/rel_1_23/unversioned.py
hikaru/model/rel_1_23/versions.py
hikaru/model/rel_1_23/v1/__init__.py
hikaru/model/rel_1_23/v1/documents.py
hikaru/model/rel_1_23/v1/v1.py
hikaru/model/rel_1_23/v1/watchables.py
hikaru/model/rel_1_23/v1alpha1/__init__.py
hikaru/model/rel_1_23/v1alpha1/documents.py
hikaru/model/rel_1_23/v1alpha1/v1alpha1.py
hikaru/model/rel_1_23/v1alpha1/watchables.py
hikaru/model/rel_1_23/v1beta1/__init__.py
hikaru/model/rel_1_23/v1beta1/documents.py
hikaru/model/rel_1_23/v1beta1/v1beta1.py
hikaru/model/rel_1_23/v1beta1/watchables.py
hikaru/model/rel_1_23/v1beta2/__init__.py
hikaru/model/rel_1_23/v1beta2/documents.py
hikaru/model/rel_1_23/v1beta2/v1beta2.py
hikaru/model/rel_1_23/v1beta2/watchables.py
hikaru/model/rel_1_23/v2/__init__.py
hikaru/model/rel_1_23/v2/documents.py
hikaru/model/rel_1_23/v2/v2.py
hikaru/model/rel_1_23/v2/watchables.py
hikaru/model/rel_1_23/v2beta1/__init__.py
hikaru/model/rel_1_23/v2beta1/documents.py
hikaru/model/rel_1_23/v2beta1/v2beta1.py
hikaru/model/rel_1_23/v2beta1/watchables.py
hikaru/model/rel_1_23/v2beta2/__init__.py
hikaru/model/rel_1_23/v2beta2/documents.py
hikaru/model/rel_1_23/v2beta2/v2beta2.py
hikaru/model/rel_1_23/v2beta2/watchables.py
hikaru_model_23-1.1.1.dist-info/LICENSE
hikaru_model_23-1.1.1.dist-info/METADATA
hikaru_model_23-1.1.1.dist-info/WHEEL
hikaru_model_23-1.1.1.dist-info/top_level.txt
hikaru_model_23-1.1.1.dist-info/RECORD
